python_spektra/__init__.py
python_spektra/checkout.py
python_spektra-0.0.1.dist-info/LICENSE
python_spektra-0.0.1.dist-info/METADATA
python_spektra-0.0.1.dist-info/WHEEL
python_spektra-0.0.1.dist-info/top_level.txt
python_spektra-0.0.1.dist-info/RECORD
